filip/__init__.py
filip/config.py
filip/custom_types.py
filip/clients/__init__.py
filip/clients/base_http_client.py
filip/clients/exceptions.py
filip/clients/mqtt/__init__.py
filip/clients/mqtt/client.py
filip/clients/mqtt/encoder/__init__.py
filip/clients/mqtt/encoder/base_encoder.py
filip/clients/mqtt/encoder/json.py
filip/clients/mqtt/encoder/ulralight.py
filip/clients/ngsi_ld/__init__.py
filip/clients/ngsi_ld/cb.py
filip/clients/ngsi_v2/__init__.py
filip/clients/ngsi_v2/cb.py
filip/clients/ngsi_v2/client.py
filip/clients/ngsi_v2/iota.py
filip/clients/ngsi_v2/quantumleap.py
filip/data/unece-units/levels.csv
filip/data/unece-units/units_of_measure.csv
filip/models/__init__.py
filip/models/base.py
filip/models/mqtt.py
filip/models/ngsi_ld/__init__.py
filip/models/ngsi_ld/base.py
filip/models/ngsi_ld/context.py
filip/models/ngsi_ld/subscriptions.py
filip/models/ngsi_v2/__init__.py
filip/models/ngsi_v2/base.py
filip/models/ngsi_v2/context.py
filip/models/ngsi_v2/iot.py
filip/models/ngsi_v2/registrations.py
filip/models/ngsi_v2/subscriptions.py
filip/models/ngsi_v2/timeseries.py
filip/models/ngsi_v2/units.py
filip/semantics/__init__.py
filip/semantics/semantics_manager.py
filip/semantics/semantics_models.py
filip/semantics/vocabulary_configurator.py
filip/semantics/ontology_parser/__init__.py
filip/semantics/ontology_parser/post_processer.py
filip/semantics/ontology_parser/rdfparser.py
filip/semantics/ontology_parser/vocabulary_builder.py
filip/semantics/vocabulary/__init__.py
filip/semantics/vocabulary/combined_relations.py
filip/semantics/vocabulary/entities.py
filip/semantics/vocabulary/relation.py
filip/semantics/vocabulary/source.py
filip/semantics/vocabulary/vocabulary.py
filip/utils/__init__.py
filip/utils/cleanup.py
filip/utils/data.py
filip/utils/datetime.py
filip/utils/filter.py
filip/utils/geo_ql.py
filip/utils/iot.py
filip/utils/model_generation.py
filip/utils/simple_ql.py
filip/utils/validators.py
filip-0.7.3.dist-info/licenses/LICENSE.md
filip-0.7.3.dist-info/METADATA
filip-0.7.3.dist-info/WHEEL
filip-0.7.3.dist-info/top_level.txt
filip-0.7.3.dist-info/RECORD
