Metadata-Version: 2.4
Name: filip
Version: 0.7.3
Summary: [FI]WARE [Li]brary for [P]ython
Home-page: https://github.com/RWTH-EBC/filip
Download-URL: https://github.com/RWTH-EBC/FiLiP/archive/refs/tags/v0.7.3.tar.gz
Author: RWTH Aachen University, E.ON Energy Research Center, Institute        of Energy Efficient Buildings and Indoor Climate
Author-email: ebc-tools@eonerc.rwth-aachen.de
Project-URL: Documentation, https://rwth-ebc.github.io/FiLiP/master/docs/index.html
Project-URL: Source, https://github.com/RWTH-EBC/filip
Project-URL: Download, https://github.com/RWTH-EBC/FiLiP/archive/refs/tags/v0.7.3.tar.gz
Keywords: iot,fiware,semantic
Classifier: Development Status :: 3 - Alpha
Classifier: Topic :: Scientific/Engineering
Classifier: Intended Audience :: Science/Research
Classifier: Programming Language :: Python :: 3.8
Classifier: Programming Language :: Python :: 3.9
Classifier: Programming Language :: Python :: 3.10
Classifier: Programming Language :: Python :: 3.11
Classifier: Programming Language :: Python :: 3.12
Classifier: License :: OSI Approved :: BSD License
Requires-Python: >=3.8
License-File: LICENSE.md
Requires-Dist: aenum~=3.1.15
Requires-Dist: datamodel_code_generator[http]~=0.25.0
Requires-Dist: paho-mqtt~=2.0.0
Requires-Dist: pandas_datapackage_reader~=0.18.0
Requires-Dist: pydantic<2.9.0,>=2.6.0
Requires-Dist: pydantic-settings<2.3.0,>=2.0.0
Requires-Dist: geojson_pydantic~=1.0.2
Requires-Dist: stringcase>=1.2.0
Requires-Dist: regex~=2023.10.3
Requires-Dist: requests~=2.32.0
Requires-Dist: rapidfuzz~=3.4.0
Requires-Dist: geojson-pydantic~=1.0.2
Requires-Dist: wget~=3.2
Requires-Dist: PyLD~=2.0.4
Requires-Dist: pyjexl~=0.3.0
Requires-Dist: packaging~=24.1
Requires-Dist: matplotlib~=3.9.4
Provides-Extra: development
Requires-Dist: pre-commit~=4.0.1; extra == "development"
Provides-Extra: semantics
Requires-Dist: igraph~=0.11.2; extra == "semantics"
Requires-Dist: rdflib<=6.1.1,>=6.0.0; extra == "semantics"
Provides-Extra: tutorials
Requires-Dist: plotly==5.24.1; extra == "tutorials"
Requires-Dist: matplotlib~=3.4.3; extra == "tutorials"
Requires-Dist: pandas~=1.3.5; python_version < "3.9"
Requires-Dist: pandas<2.4.0,>=2.1.4; python_version >= "3.9"
Dynamic: author
Dynamic: author-email
Dynamic: classifier
Dynamic: description
Dynamic: description-content-type
Dynamic: download-url
Dynamic: home-page
Dynamic: keywords
Dynamic: license-file
Dynamic: project-url
Dynamic: provides-extra
Dynamic: requires-dist
Dynamic: requires-python
Dynamic: summary
